setup.py
cinrad_data/__init__.py
cinrad_data.egg-info/PKG-INFO
cinrad_data.egg-info/SOURCES.txt
cinrad_data.egg-info/dependency_links.txt
cinrad_data.egg-info/top_level.txt
cinrad_data/font/LICENSE_CJK.txt
cinrad_data/font/NotoSansHans-Regular.otf
cinrad_data/shapefile/City.dbf
cinrad_data/shapefile/City.prj
cinrad_data/shapefile/City.sbn
cinrad_data/shapefile/City.sbx
cinrad_data/shapefile/City.shp
cinrad_data/shapefile/City.shp.xml
cinrad_data/shapefile/City.shx
cinrad_data/shapefile/City.xml
cinrad_data/shapefile/County.dbf
cinrad_data/shapefile/County.prj
cinrad_data/shapefile/County.sbn
cinrad_data/shapefile/County.sbx
cinrad_data/shapefile/County.shp
cinrad_data/shapefile/County.shp.xml
cinrad_data/shapefile/County.shx
cinrad_data/shapefile/County.xml
cinrad_data/shapefile/Province.dbf
cinrad_data/shapefile/Province.prj
cinrad_data/shapefile/Province.sbn
cinrad_data/shapefile/Province.sbx
cinrad_data/shapefile/Province.shp
cinrad_data/shapefile/Province.shp.xml
cinrad_data/shapefile/Province.shx
cinrad_data/shapefile/Province.xml