Metadata-Version: 2.1
Name: cinrad-data
Version: 0.1
Summary: Data files for cinrad module
Home-page: UNKNOWN
Author: Puyuan Du
Author-email: dpy274555447@gmail.com
License: MIT Licence
Platform: Windows
